<?xml version="1.0" encoding="UTF-8"?>
<con:resource name="/v2/pet/101" path="/v2/pet/101" id="65fab7b3-eb62-47aa-80ee-d19fe2a64d66" xmlns:xsi="http://www.w3.org/2001/XMLSchema-instance" xmlns:con="http://eviware.com/soapui/config"><con:settings><con:setting id="65fab7b3-eb62-47aa-80ee-d19fe2a64d66fileName">%2Fv2%2Fpet%2F101</con:setting></con:settings><con:parameters/><con:method name="POST" id="05e196d0-4f83-4eb6-a4c2-747ddab0c140" method="POST"><con:settings/><con:parameters/><con:request name="POST Request" id="966c5681-404d-445c-98d3-0477150ccce8" mediaType="application/json"><con:settings/><con:endpoint>https://petstore.swagger.io</con:endpoint><con:credentials><con:selectedAuthProfile>No Authorization</con:selectedAuthProfile><con:authType>No Authorization</con:authType></con:credentials><con:parameters/></con:request></con:method></con:resource>